testpath/__init__.py
testpath/asserts.py
testpath/cli-32.exe
testpath/cli-64.exe
testpath/commands.py
testpath/env.py
testpath/tempdir.py
testpath-0.4.3.dist-info//tmp/tmpsad01phf/testpath-0.4.3/LICENSE
testpath-0.4.3.dist-info/WHEEL
testpath-0.4.3.dist-info/METADATA
testpath-0.4.3.dist-info/RECORD
