Metadata-Version: 2.1
Name: testpath
Version: 0.4.3
Summary: Test utilities for code working with files and commands
Home-page: https://github.com/jupyter/testpath
License: UNKNOWN
Author: Jupyter Development Team
Author-email: jupyter@googlegroups.com
Classifier: Intended Audience :: Developers
Classifier: License :: OSI Approved :: BSD License
Classifier: Programming Language :: Python
Classifier: Programming Language :: Python :: 2
Classifier: Programming Language :: Python :: 3
Classifier: Topic :: Software Development :: Testing
Requires-Dist: pathlib2; extra == "test" and ( python_version == "2.7")
Project-URL: Documentation, https://testpath.readthedocs.io/en/latest/
Provides-Extra: test
